{
  "contractName": "VerificationBuffer",
  "address": "0xBf47D97f75EC66BFdaC3bBe9E3DBFFce9D57C295",
  "network": "hedera_testnet",
  "sourceFile": "VerificationBuffer.sol",
  "metadataFile": "VerificationBuffer.json",
  "constructorArgs": [],
  "hashscanUrl": "https://hashscan.io/testnet/contract/0xBf47D97f75EC66BFdaC3bBe9E3DBFFce9D57C295",
  "verificationSteps": [
    "1. Go to the HashScan URL above",
    "2. Click 'Verify' in the Contract Bytecode section",
    "3. Upload the .sol source file",
    "4. Upload the .json metadata file",
    "5. Enter constructor arguments if any",
    "6. Click 'VERIFY' to submit"
  ]
}